perfectmoney/__init__.py
perfectmoney/links.py
perfectmoney/perfectmoney.py
perfectmoney/requests.py
perfectmoney/utils.py
perfectmoney-2.1.4.dist-info/LICENSE
perfectmoney-2.1.4.dist-info/METADATA
perfectmoney-2.1.4.dist-info/WHEEL
perfectmoney-2.1.4.dist-info/top_level.txt
perfectmoney-2.1.4.dist-info/RECORD
