Metadata-Version: 2.1
Name: perfectmoney
Version: 2.1.4
Summary: API for PerfectMoney service
Home-page: https://github.com/quitegreensky/perfectmoney
Author: Sina Namadian
Author-email: quitegreensky@gmail.com
License: MIT
Platform: UNKNOWN
Classifier: Programming Language :: Python :: 3
Classifier: License :: OSI Approved :: MIT License
Requires-Dist: requests
Requires-Dist: xmltodict
